schedule_mcp_server/__init__.py
schedule_mcp_server/schedule.csv
schedule_mcp_server-0.1.2.dist-info/METADATA
schedule_mcp_server-0.1.2.dist-info/WHEEL
schedule_mcp_server-0.1.2.dist-info/entry_points.txt
schedule_mcp_server-0.1.2.dist-info/RECORD
